czastc/__init__.py
czastc/module.py
czastc/turtle/__init__.py
czastc/turtle/paint.py
czastc-0.0.1a9.dist-info/LICENSE
czastc-0.0.1a9.dist-info/METADATA
czastc-0.0.1a9.dist-info/WHEEL
czastc-0.0.1a9.dist-info/top_level.txt
czastc-0.0.1a9.dist-info/RECORD
