Metadata-Version: 2.1
Name: czastc
Version: 0.0.1a9
Summary: A testing python package
Home-page: https://github.com/CZAsTc/CZAsTc-Python-Library
Author: CZAsTC
Author-email: chensukai43@outlook.com
License: Apache-2.0
Classifier: Development Status :: 3 - Alpha
Classifier: License :: OSI Approved :: Apache Software License
Classifier: Programming Language :: Python :: 3
Classifier: Operating System :: OS Independent
License-File: LICENSE
